hawk_python_sdk/__init__.py
hawk_python_sdk/core.py
hawk_python_sdk/errors.py
hawk_python_sdk/types.py
hawk_python_sdk/modules/fastapi/__init__.py
hawk_python_sdk/modules/fastapi/fastapi.py
hawk_python_sdk/modules/fastapi/types.py
hawk_python_sdk/modules/flask/__init__.py
hawk_python_sdk/modules/flask/flask.py
hawk_python_sdk/modules/flask/types.py
hawk_python_sdk-3.5.1.dist-info/METADATA
hawk_python_sdk-3.5.1.dist-info/WHEEL
hawk_python_sdk-3.5.1.dist-info/licenses/LICENSE
hawk_python_sdk-3.5.1.dist-info/RECORD
