Metadata-Version: 2.4
Name: hawk-python-sdk
Version: 3.5.1
Summary: Python errors Catcher module for Hawk.
Project-URL: Homepage, https://github.com/codex-team/hawk.python
Project-URL: Issues, https://github.com/codex-team/hawk.python/issues
Author-email: CodeX Team <team@codex.so>
License-File: LICENSE
Classifier: Environment :: Console
Classifier: Environment :: Web Environment
Classifier: Intended Audience :: Developers
Classifier: License :: OSI Approved :: MIT License
Classifier: Programming Language :: Python :: 3.5
Classifier: Topic :: Software Development :: Bug Tracking
Requires-Python: >=3.9
Requires-Dist: requests
Provides-Extra: fastapi
Requires-Dist: starlette; extra == 'fastapi'
Provides-Extra: flask
Requires-Dist: flask; extra == 'flask'
